<?xml version="1.0" encoding="utf-8"?>
<history version="1.0"><sql type="query"><database>wenxue2</database><datetime>41601.7601180903</datetime><fields>13</fields><records>1259</records><rows_affected>0</rows_affected><sql>select * from wenxue where aid3=0</sql><execution_time>0</execution_time></sql><sql type="query"><database>wenxue2</database><datetime>41601.807507338</datetime><fields>13</fields><records>1259</records><rows_affected>0</rows_affected><sql>select * from wenxue where aid3=0</sql><execution_time>2.31448211707175E-8</execution_time></sql><sql type="query"><database>wenxue2</database><datetime>41601.8076086921</datetime><fields>13</fields><records>1259</records><rows_affected>0</rows_affected><sql>select * from wenxue where aid3=0</sql><execution_time>4.62969182990491E-8</execution_time></sql><sql type="query"><database>wenxue2</database><datetime>41601.8076172338</datetime><fields>13</fields><records>1259</records><rows_affected>0</rows_affected><sql>select * from wenxue where aid3=0</sql><execution_time>5.7872966863215E-8</execution_time></sql><sql type="query"><database>wenxue2</database><datetime>41601.8076255093</datetime><fields>13</fields><records>1259</records><rows_affected>0</rows_affected><sql>select * from wenxue where aid3=0</sql><execution_time>5.7872966863215E-8</execution_time></sql><sql type="query"><database>wenxue2</database><datetime>41601.8101834722</datetime><fields>13</fields><records>1259</records><rows_affected>0</rows_affected><sql>select * from wenxue where aid3=0</sql><execution_time>4.62969182990491E-8</execution_time></sql><sql type="statement"><database>wenxue2</database><datetime>41601.8101914468</datetime><fields>0</fields><records>376</records><rows_affected>0</rows_affected><sql></sql><execution_time>5.7872966863215E-8</execution_time></sql><sql type="query"><database>wenxue2</database><datetime>41601.8181346991</datetime><fields>13</fields><records>1259</records><rows_affected>0</rows_affected><sql>select * from wenxue where aid3=0</sql><execution_time>1.85187673196197E-7</execution_time></sql><sql type="query"><database>wenxue2</database><datetime>41601.8189439005</datetime><fields>13</fields><records>1259</records><rows_affected>0</rows_affected><sql>select * from wenxue where aid3=0</sql><execution_time>5.78656909056008E-8</execution_time></sql><sql type="query"><database>spring</database><datetime>43561.7698120718</datetime><fields>3</fields><records>5</records><sql>select  *  from account;</sql><execution_time>2.31448211707175E-8</execution_time></sql><sql type="statement"><database>mybatis9</database><datetime>43571.7261398958</datetime><fields>0</fields><records>0</records><rows_affected>0</rows_affected><sql>CREATE table tb_passprotect(
pp_id int,
queation varchar(255) not null,
answer varchar(255) not null,
foreign key(pp_id) references tb_student(stu_id) on delete cascade on update cascade
);</sql><execution_time>7.63895513955504E-7</execution_time></sql><sql type="statement"><database>system_user</database><datetime>43571.755049375</datetime><fields>0</fields><records>0</records><rows_affected>1</rows_affected><sql>insert into tb_student(stu_id,userName,sex,age,e_mail,grade,school) values(NULL,'张三','男','34','123567899','六','太空大学');</sql><execution_time>2.31520971283317E-8</execution_time><insert_id>2</insert_id></sql><sql type="statement"><database>system_user</database><datetime>43571.7551893056</datetime><fields>0</fields><records>0</records><rows_affected>1</rows_affected><sql>insert into tb_student(stu_id,userName,sex,age,e_mail,grade,school) values(NULL,'张三','男','34','123567899','六','太空大学');</sql><execution_time>6.94490154273808E-8</execution_time><insert_id>3</insert_id></sql><sql type="statement"><database>system_user</database><datetime>43571.7552085417</datetime><fields>0</fields><records>0</records><rows_affected>1</rows_affected><sql>insert into tb_student(stu_id,userName,sex,age,e_mail,grade,school) values(NULL,'张三','男','34','123567899','六','太空大学');</sql><execution_time>2.31520971283317E-8</execution_time><insert_id>4</insert_id></sql><sql type="statement"><database>system_user</database><datetime>43571.7552233102</datetime><fields>0</fields><records>0</records><rows_affected>1</rows_affected><sql>insert into tb_student(stu_id,userName,sex,age,e_mail,grade,school) values(NULL,'张三','男','34','123567899','六','太空大学');</sql><execution_time>4.62969182990491E-8</execution_time><insert_id>5</insert_id></sql><sql type="statement"><database>system_user</database><datetime>43571.7552349306</datetime><fields>0</fields><records>0</records><rows_affected>1</rows_affected><sql>insert into tb_student(stu_id,userName,sex,age,e_mail,grade,school) values(NULL,'张三','男','34','123567899','六','太空大学');</sql><execution_time>2.31448211707175E-8</execution_time><insert_id>6</insert_id></sql><sql type="statement"><database>system_user</database><datetime>43571.7552407986</datetime><fields>0</fields><records>0</records><rows_affected>1</rows_affected><sql>insert into tb_student(stu_id,userName,sex,age,e_mail,grade,school) values(NULL,'张三','男','34','123567899','六','太空大学');</sql><execution_time>1.15738657768816E-7</execution_time><insert_id>7</insert_id></sql><sql type="statement"><database>system_user</database><datetime>43571.7552448611</datetime><fields>0</fields><records>0</records><rows_affected>1</rows_affected><sql>insert into tb_student(stu_id,userName,sex,age,e_mail,grade,school) values(NULL,'张三','男','34','123567899','六','太空大学');</sql><execution_time>3.47208697348833E-8</execution_time><insert_id>8</insert_id></sql><sql type="statement"><database>system_user</database><datetime>43571.7552487037</datetime><fields>0</fields><records>0</records><rows_affected>1</rows_affected><sql>insert into tb_student(stu_id,userName,sex,age,e_mail,grade,school) values(NULL,'张三','男','34','123567899','六','太空大学');</sql><execution_time>5.7872966863215E-8</execution_time><insert_id>9</insert_id></sql><sql type="statement"><database>system_user</database><datetime>43571.7552538542</datetime><fields>0</fields><records>0</records><rows_affected>1</rows_affected><sql>insert into tb_student(stu_id,userName,sex,age,e_mail,grade,school) values(NULL,'张三','男','34','123567899','六','太空大学');</sql><execution_time>2.31448211707175E-8</execution_time><insert_id>10</insert_id></sql><sql type="statement"><database>system_user</database><datetime>43571.7552589352</datetime><fields>0</fields><records>0</records><rows_affected>1</rows_affected><sql>insert into tb_student(stu_id,userName,sex,age,e_mail,grade,school) values(NULL,'张三','男','34','123567899','六','太空大学');</sql><execution_time>2.31448211707175E-8</execution_time><insert_id>11</insert_id></sql><sql type="statement"><database>system_user</database><datetime>43571.7552641667</datetime><fields>0</fields><records>0</records><rows_affected>1</rows_affected><sql>insert into tb_student(stu_id,userName,sex,age,e_mail,grade,school) values(NULL,'张三','男','34','123567899','六','太空大学');</sql><execution_time>2.31448211707175E-8</execution_time><insert_id>12</insert_id></sql><sql type="statement"><database>system_user</database><datetime>43571.7552688542</datetime><fields>0</fields><records>0</records><rows_affected>1</rows_affected><sql>insert into tb_student(stu_id,userName,sex,age,e_mail,grade,school) values(NULL,'张三','男','34','123567899','六','太空大学');</sql><execution_time>2.31448211707175E-8</execution_time><insert_id>13</insert_id></sql><sql type="statement"><database>system_user</database><datetime>43571.7552721296</datetime><fields>0</fields><records>0</records><rows_affected>1</rows_affected><sql>insert into tb_student(stu_id,userName,sex,age,e_mail,grade,school) values(NULL,'张三','男','34','123567899','六','太空大学');</sql><execution_time>1.15738657768816E-7</execution_time><insert_id>14</insert_id></sql><sql type="statement"><database>system_user</database><datetime>43571.7552740509</datetime><fields>0</fields><records>0</records><rows_affected>1</rows_affected><sql>insert into tb_student(stu_id,userName,sex,age,e_mail,grade,school) values(NULL,'张三','男','34','123567899','六','太空大学');</sql><execution_time>6.94490154273808E-8</execution_time><insert_id>15</insert_id></sql><sql type="statement"><database>system_user</database><datetime>43571.7552759028</datetime><fields>0</fields><records>0</records><rows_affected>1</rows_affected><sql>insert into tb_student(stu_id,userName,sex,age,e_mail,grade,school) values(NULL,'张三','男','34','123567899','六','太空大学');</sql><execution_time>2.31448211707175E-8</execution_time><insert_id>16</insert_id></sql><sql type="statement"><database>system_user</database><datetime>43571.7552778704</datetime><fields>0</fields><records>0</records><rows_affected>1</rows_affected><sql>insert into tb_student(stu_id,userName,sex,age,e_mail,grade,school) values(NULL,'张三','男','34','123567899','六','太空大学');</sql><execution_time>3.47208697348833E-8</execution_time><insert_id>17</insert_id></sql></history>
